{
	"name": "trigger1",
	"properties": {
		"annotations": [],
		"runtimeState": "Stopped",
		"pipelines": [
			{
				"pipelineReference": {
					"referenceName": "vw_cliente",
					"type": "PipelineReference"
				}
			}
		],
		"type": "ScheduleTrigger",
		"typeProperties": {
			"recurrence": {
				"frequency": "Month",
				"interval": 15,
				"startTime": "2023-09-13T19:53:00",
				"endTime": "2023-09-15T00:50:00",
				"timeZone": "SA Pacific Standard Time",
				"schedule": {
					"monthDays": [
						1
					]
				}
			}
		}
	}
}